openctp_ctpopt/soptthostmduserapi.py
openctp_ctpopt/soptthosttraderapi.py
openctp_ctpopt/_soptthostmduserapi.pyd
openctp_ctpopt/_soptthosttraderapi.pyd
openctp_ctpopt/__init__.py
openctp_ctpopt-3.7.3.1.dist-info/DELVEWHEEL
openctp_ctpopt-3.7.3.1.dist-info/LICENSE
openctp_ctpopt-3.7.3.1.dist-info/METADATA
openctp_ctpopt-3.7.3.1.dist-info/RECORD
openctp_ctpopt-3.7.3.1.dist-info/top_level.txt
openctp_ctpopt-3.7.3.1.dist-info/WHEEL
openctp_ctpopt.libs/soptthostmduserapi_se-24943d06fa1eaf1d9f46699a3a694d1b.dll
openctp_ctpopt.libs/soptthosttraderapi_se-097a7e395747b53e01ec9ea9a0f95594.dll
